pyqusim/__init__.py
pyqusim/binary_qubit_gate.py
pyqusim/circuit.py
pyqusim/ctx.py
pyqusim/ctx_funcs.py
pyqusim/ctx_funcs.pyi
pyqusim/measure.py
pyqusim/qft.py
pyqusim/qpu.py
pyqusim/runnable.py
pyqusim/typing.py
pyqusim/unary_qubit_gate.py
pyqusim/utils.py
pyqusim-0.1.2.dist-info/METADATA
pyqusim-0.1.2.dist-info/WHEEL
pyqusim-0.1.2.dist-info/licenses/LICENSE
pyqusim-0.1.2.dist-info/RECORD
